ssd1306_plus.py
ssd1306_plus-0.0.5.dist-info/METADATA
ssd1306_plus-0.0.5.dist-info/WHEEL
ssd1306_plus-0.0.5.dist-info/licenses/LICENSE
ssd1306_plus-0.0.5.dist-info/RECORD
