Metadata-Version: 2.1
Name: ssd1306_plus
Version: 0.0.5
Summary: Augments the SSD1306_I2C MicroPython library with high-level functions
Author-email: Code Cadets <codecadets@cgs.act.edu.au>
License-File: LICENSE
Classifier: License :: OSI Approved :: MIT License
Classifier: Operating System :: OS Independent
Classifier: Programming Language :: Python :: Implementation :: MicroPython
